[
    {
        "id": "P1 1.1KW",
        "impellers": [
            {
                "diameter_mm": 110,
                "capacity_range_Lhr": [ 0, 16000 ],
                "pressure_range_bar": [ 0.10, 0.52 ]
            },
            {
                "diameter_mm": 120,
                "capacity_range_Lhr": [ 0, 19000 ],
                "pressure_range_bar": [ 0.15, 0.62 ]
            },
            {
                "diameter_mm": 130,
                "capacity_range_Lhr": [ 0, 22000 ],
                "pressure_range_bar": [ 0.20, 0.71 ]
            },
            {
                "diameter_mm": 140,
                "capacity_range_Lhr": [ 0, 24500 ],
                "pressure_range_bar": [ 0.25, 0.80 ]
            },
            {
                "diameter_mm": 150,
                "capacity_range_Lhr": [ 0, 26500 ],
                "pressure_range_bar": [ 0.30, 0.88 ]
            },
            {
                "diameter_mm": 160,
                "capacity_range_Lhr": [ 0, 28000 ],
                "pressure_range_bar": [ 0.35, 0.93 ]
            },
            {
                "diameter_mm": 171,
                "capacity_range_Lhr": [ 0, 29000 ],
                "pressure_range_bar": [ 0.40, 0.98 ]
            }
        ]
    },
    {
        "id": "P1 2.2KW",
        "impellers": [
            {
                "diameter_mm": 110,
                "capacity_range_Lhr": [ 0, 38000 ],
                "pressure_range_bar": [ 0.40, 1.30 ]
            },
            {
                "diameter_mm": 120,
                "capacity_range_Lhr": [ 0, 37000 ],
                "pressure_range_bar": [ 0.80, 1.70 ]
            },
            {
                "diameter_mm": 130,
                "capacity_range_Lhr": [ 0, 35000 ],
                "pressure_range_bar": [ 1.30, 2.25 ]
            },
            {
                "diameter_mm": 140,
                "capacity_range_Lhr": [ 0, 33000 ],
                "pressure_range_bar": [ 1.80, 2.80 ]
            },
            {
                "diameter_mm": 150,
                "capacity_range_Lhr": [ 0, 30000 ],
                "pressure_range_bar": [ 2.40, 3.30 ]
            },
            {
                "diameter_mm": 160,
                "capacity_range_Lhr": [ 0, 28000 ],
                "pressure_range_bar": [ 3.00, 3.80 ]
            },
            {
                "diameter_mm": 171,
                "capacity_range_Lhr": [ 0, 25000 ],
                "pressure_range_bar": [ 3.40, 4.20 ]
            }
        ]
    },
    {
        "id": "P1 5.5KW",
        "impellers": [
            {
                "diameter_mm": 140,
                "capacity_range_Lhr": [ 0, 42000 ],
                "pressure_range_bar": [ 1.70, 2.90 ]
            },
            {
                "diameter_mm": 150,
                "capacity_range_Lhr": [ 0, 38000 ],
                "pressure_range_bar": [ 2.30, 3.40 ]
            },
            {
                "diameter_mm": 160,
                "capacity_range_Lhr": [ 0, 34000 ],
                "pressure_range_bar": [ 2.80, 4.00 ]
            },
            {
                "diameter_mm": 171,
                "capacity_range_Lhr": [ 0, 30000 ],
                "pressure_range_bar": [ 3.20, 4.60 ]
            }
        ]
    },
    {
        "id": "P2 5.5KW",
        "impellers": [
            {
                "diameter_mm": 170,
                "capacity_range_Lhr": [ 0, 38000 ],
                "pressure_range_bar": [ 0.40, 1.10 ]
            },
            {
                "diameter_mm": 190,
                "capacity_range_Lhr": [ 0, 44000 ],
                "pressure_range_bar": [ 0.55, 1.35 ]
            },
            {
                "diameter_mm": 200,
                "capacity_range_Lhr": [ 0, 47000 ],
                "pressure_range_bar": [ 0.60, 1.50 ]
            },
            {
                "diameter_mm": 210,
                "capacity_range_Lhr": [ 0, 50000 ],
                "pressure_range_bar": [ 0.70, 1.65 ]
            },
            {
                "diameter_mm": 220,
                "capacity_range_Lhr": [ 0, 52500 ],
                "pressure_range_bar": [ 0.80, 1.80 ]
            },
            {
                "diameter_mm": 230,
                "capacity_range_Lhr": [ 0, 55000 ],
                "pressure_range_bar": [ 0.90, 1.95 ]
            },
            {
                "diameter_mm": 240,
                "capacity_range_Lhr": [ 0, 57000 ],
                "pressure_range_bar": [ 1.05, 2.10 ]
            },
            {
                "diameter_mm": 250,
                "capacity_range_Lhr": [ 0, 58000 ],
                "pressure_range_bar": [ 1.20, 2.20 ]
            }
        ]
    },
    {
        "id": "P2 7.5KW",
        "impellers": [
            {
                "diameter_mm": 120,
                "capacity_range_Lhr": [ 0, 52000 ],
                "pressure_range_bar": [ 0.50, 2.00 ]
            },
            {
                "diameter_mm": 130,
                "capacity_range_Lhr": [ 0, 50000 ],
                "pressure_range_bar": [ 0.90, 2.40 ]
            },
            {
                "diameter_mm": 140,
                "capacity_range_Lhr": [ 0, 48000 ],
                "pressure_range_bar": [ 1.30, 2.90 ]
            },
            {
                "diameter_mm": 150,
                "capacity_range_Lhr": [ 0, 45000 ],
                "pressure_range_bar": [ 1.80, 3.45 ]
            },
            {
                "diameter_mm": 160,
                "capacity_range_Lhr": [ 0, 41000 ],
                "pressure_range_bar": [ 2.40, 4.00 ]
            },
            {
                "diameter_mm": 170,
                "capacity_range_Lhr": [ 0, 36000 ],
                "pressure_range_bar": [ 3.00, 4.50 ]
            },
            {
                "diameter_mm": 180,
                "capacity_range_Lhr": [ 0, 31000 ],
                "pressure_range_bar": [ 3.80, 5.00 ]
            },
            {
                "diameter_mm": 190,
                "capacity_range_Lhr": [ 0, 25000 ],
                "pressure_range_bar": [ 4.80, 5.40 ]
            }
        ]
    },
    {
        "id": "PS 0.75KW",
        "impellers": [
            {
                "diameter_mm": 110,
                "capacity_range_Lhr": [ 0, 12500 ],
                "pressure_range_bar": [ 0.10, 0.42 ]
            },
            {
                "diameter_mm": 115,
                "capacity_range_Lhr": [ 0, 13500 ],
                "pressure_range_bar": [ 0.15, 0.46 ]
            }
        ]
    },
    {
        "id": "PS 1.1KW",
        "impellers": [
            {
                "diameter_mm": 110,
                "capacity_range_Lhr": [ 0, 16500 ],
                "pressure_range_bar": [ 1.00, 1.60 ]
            },
            {
                "diameter_mm": 115,
                "capacity_range_Lhr": [ 0, 14500 ],
                "pressure_range_bar": [ 1.25, 1.80 ]
            }
        ]
    },
    {
        "id": "PT 0.55KW",
        "impellers": [
            {
                "diameter_mm": "92",
                "capacity_range_Lhr": [ 0, 12000 ],
                "pressure_range_bar": [ 0.70, 1.15 ]
            }
        ]
    },
    {
        "id": "P1 3.0KW",
        "impellers": [
            {
                "diameter_mm": 110,
                "capacity_range_Lhr": [ 0, 38000 ],
                "pressure_range_bar": [ 0.40, 1.30 ]
            },
            {
                "diameter_mm": 120,
                "capacity_range_Lhr": [ 0, 37000 ],
                "pressure_range_bar": [ 0.80, 1.70 ]
            },
            {
                "diameter_mm": 130,
                "capacity_range_Lhr": [ 0, 35000 ],
                "pressure_range_bar": [ 1.30, 2.25 ]
            },
            {
                "diameter_mm": 140,
                "capacity_range_Lhr": [ 0, 33000 ],
                "pressure_range_bar": [ 1.80, 2.80 ]
            },
            {
                "diameter_mm": 150,
                "capacity_range_Lhr": [ 0, 30000 ],
                "pressure_range_bar": [ 2.40, 3.30 ]
            },
            {
                "diameter_mm": 160,
                "capacity_range_Lhr": [ 0, 28000 ],
                "pressure_range_bar": [ 3.00, 3.80 ]
            },
            {
                "diameter_mm": 171,
                "capacity_range_Lhr": [ 0, 25000 ],
                "pressure_range_bar": [ 3.40, 4.20 ]
            }
        ]
    },
    {
        "id": "P1 4.0KW",
        "impellers": [
            {
                "diameter_mm": 110,
                "capacity_range_Lhr": [ 0, 38000 ],
                "pressure_range_bar": [ 0.40, 1.30 ]
            },
            {
                "diameter_mm": 120,
                "capacity_range_Lhr": [ 0, 37000 ],
                "pressure_range_bar": [ 0.80, 1.70 ]
            },
            {
                "diameter_mm": 130,
                "capacity_range_Lhr": [ 0, 35000 ],
                "pressure_range_bar": [ 1.30, 2.25 ]
            },
            {
                "diameter_mm": 140,
                "capacity_range_Lhr": [ 0, 33000 ],
                "pressure_range_bar": [ 1.80, 2.80 ]
            },
            {
                "diameter_mm": 150,
                "capacity_range_Lhr": [ 0, 30000 ],
                "pressure_range_bar": [ 2.40, 3.30 ]
            },
            {
                "diameter_mm": 160,
                "capacity_range_Lhr": [ 0, 28000 ],
                "pressure_range_bar": [ 3.00, 3.80 ]
            },
            {
                "diameter_mm": 171,
                "capacity_range_Lhr": [ 0, 25000 ],
                "pressure_range_bar": [ 3.40, 4.20 ]
            }
        ]
    }
]